mkrdf.py
mkrdf-0.2.3.dist-info/METADATA
mkrdf-0.2.3.dist-info/WHEEL
mkrdf-0.2.3.dist-info/entry_points.txt
mkrdf-0.2.3.dist-info/licenses/LICENSE.txt
mkrdf-0.2.3.dist-info/RECORD
