Metadata-Version: 2.4
Name: mkrdf
Version: 0.2.3
Summary: 
License-Expression: EUPL-1.2
License-File: LICENSE.txt
Author: Natanael Arndt
Author-email: arndtn@gmail.com
Requires-Python: >=3.11,<4.0
Classifier: Programming Language :: Python :: 3
Classifier: Programming Language :: Python :: 3.11
Classifier: Programming Language :: Python :: 3.12
Classifier: Programming Language :: Python :: 3.13
Classifier: Programming Language :: Python :: 3.14
Requires-Dist: jinja-rdf (>=0.1.5,<0.2.0)
Requires-Dist: loguru (>=0.7.3,<0.8.0)
Requires-Dist: mkdocs (>=1.6.1,<2.0.0)
Requires-Dist: rdflib (>=7.1.4,<9.0.0)
Project-URL: Repository, https://github.com/aksw/mkrdf
